sim/tb.v
/******************************************************************************
* |----------------------------------------------------------------------------|
* |                      Copyright (C) 2024-2025 VeryLag.                      |
* |                                                                            |
* | THIS SOURCE CODE IS FOR PERSONAL DEVELOPEMENT; OPEN FOR ALL USES BY ANYONE.|
* |                                                                            |
* |   Feel free to modify and use this code, but attribution is appreciated.   |
* |                                                                            |
* |----------------------------------------------------------------------------|
*
* Author : VeryLag (verylag0401@gmail.com)
* 
* Creat : 2025/04/03
* 
* Description : testbench
* 
******************************************************************************/
`timescale 1ns/1ns
module tb();

reg [3:0] cnt;

initial begin
    cnt = 'h0;
    forever #10 cnt = cnt + 1;
end

always @ (cnt) begin
    $display ("[testbench] @ %0t: cnt = 'h%0h", $time, cnt);
    if (cnt == 'hf) $finish;
end

initial begin
    $timeformat(-9, 2, " ns", 0);
    $dumpfile("tb.vcd");
    $dumpvars(0, tb);
end

endmodule

run/tb.vcd
$date
	Fri Aug 01 12:06:22 2025
$end
$version
	Icarus Verilog
$end
$timescale
	1ns
$end
$scope module tb $end
$var reg 4 ! cnt [3:0] $end
$upscope $end
$enddefinitions $end
#0
$dumpvars
b0 !
$end
#10
b1 !
#20
b10 !
#30
b11 !
#40
b100 !
#50
b101 !
#60
b110 !
#70
b111 !
#80
b1000 !
#90
b1001 !
#100
b1010 !
#110
b1011 !
#120
b1100 !
#130
b1101 !
#140
b1110 !
#150
b1111 !
